tests/__init__.py
tests/test_menu.py
tests/test_search.py
tests/test_ui.py
zlibtui/__init__.py
zlibtui/app.py
zlibtui/browser.py
zlibtui/command_line.py
zlibtui/commnad_line.py
zlibtui/menu.py
zlibtui/search.py
zlibtui/ui.py
zlibtui-1.1.2.dist-info/LICENSE
zlibtui-1.1.2.dist-info/METADATA
zlibtui-1.1.2.dist-info/WHEEL
zlibtui-1.1.2.dist-info/entry_points.txt
zlibtui-1.1.2.dist-info/top_level.txt
zlibtui-1.1.2.dist-info/RECORD
