Metadata-Version: 2.1
Name: zlibtui
Version: 1.1.2
Summary: Terminal user interface for Z-library
Home-page: https://github.com/jfto23/zibtui
Author: Jean-Francois To
Author-email: jeanfrancoisto@hotmail.com
License: UNKNOWN
Platform: UNKNOWN
Classifier: Programming Language :: Python :: 3
Classifier: License :: OSI Approved :: MIT License
Classifier: Operating System :: OS Independent
Requires-Python: >=3.6
Requires-Dist: beautifulsoup4
Requires-Dist: blessed
Requires-Dist: requests
